facts_generator/__init__.py
facts_generator/convert.py
facts_generator/dev_cisco.py
facts_generator/dev_juniper.py
facts_generator/exec_ro.py
facts_generator/init_tasks.py
facts_generator/tasks.py
facts_generator/templates.py
facts_generator-0.0.6.dist-info/LICENSE
facts_generator-0.0.6.dist-info/METADATA
facts_generator-0.0.6.dist-info/WHEEL
facts_generator-0.0.6.dist-info/top_level.txt
facts_generator-0.0.6.dist-info/RECORD
