Metadata-Version: 2.1
Name: facts-generator
Version: 0.0.6
Summary: Excel Facts File Generate from Networking Device Output|Config
Home-page: https://github.com/aliasgar1978/facts_generator
Author: ALIASGAR - ALI
Author-email: aholo2000@gmail.com
License: UNKNOWN
Platform: UNKNOWN
Classifier: Programming Language :: Python :: 3
Classifier: License :: OSI Approved :: MIT License
Classifier: Operating System :: OS Independent
Requires-Python: >=3.7
License-File: LICENSE
Requires-Dist: xlrd
Requires-Dist: pandas
Requires-Dist: openpyxl
Requires-Dist: nettoolkit
